fzf_wal/__init__.py
fzf_wal/__main__.py
fzf_wal/fzf_wal.py
fzf_wal-0.1.0.dist-info/AUTHORS.rst
fzf_wal-0.1.0.dist-info/LICENSE
fzf_wal-0.1.0.dist-info/METADATA
fzf_wal-0.1.0.dist-info/WHEEL
fzf_wal-0.1.0.dist-info/entry_points.txt
fzf_wal-0.1.0.dist-info/top_level.txt
fzf_wal-0.1.0.dist-info/RECORD
