Metadata-Version: 2.1
Name: fzf-wal
Version: 0.1.0
Summary: pywal theme selector using fzf
Home-page: https://github.com/shanedabes/fzf_wal
Author: "Shane Donohoe
Author-email: shane@donohoe.cc
License: Apache Software License 2.0
Keywords: fzf_wal
Platform: UNKNOWN
Classifier: License :: OSI Approved :: Apache Software License
Classifier: Natural Language :: English
Classifier: Programming Language :: Python :: 3
Classifier: Programming Language :: Python :: 3.6
Classifier: Programming Language :: Python :: 3.7
Requires-Dist: pywal (==3.3.0)
Requires-Dist: iterfzf (==0.4.0.17.3)
